pdfcompare/__init__.py
pdfcompare/cli.py
pdfcompare/file_handlers/__init__.py
pdfcompare/file_handlers/docx_handler.py
pdfcompare/file_handlers/epub_handler.py
pdfcompare/file_handlers/image_handler.py
pdfcompare/file_handlers/odt_handler.py
pdfcompare/file_handlers/pdf_handler.py
pdfcompare/file_handlers/txt_handler.py
tests/__init__.py
tests/test_pdfcompare.py
pdfcompare-0.2.0.dist-info/LICENSE
pdfcompare-0.2.0.dist-info/METADATA
pdfcompare-0.2.0.dist-info/WHEEL
pdfcompare-0.2.0.dist-info/entry_points.txt
pdfcompare-0.2.0.dist-info/top_level.txt
pdfcompare-0.2.0.dist-info/RECORD
