Metadata-Version: 2.1
Name: pdfcompare
Version: 0.2.0
Summary: A Python package to compare files (PDF, docx, images) and generate reports in txt, html, or PDF format
Home-page: https://github.com/imshahinul/pdfcompare
Author: S M Shahinul Islam
Author-email: s.m.shahinul.islam@gmail.com
Classifier: Programming Language :: Python :: 3
Classifier: License :: OSI Approved :: MIT License
Classifier: Operating System :: OS Independent
Requires-Python: >=3.6
License-File: LICENSE
Requires-Dist: backports.tarfile ==1.2.0
Requires-Dist: beautifulsoup4 ==4.12.3
Requires-Dist: certifi ==2024.8.30
Requires-Dist: chardet ==5.2.0
Requires-Dist: charset-normalizer ==3.4.0
Requires-Dist: ci-info ==0.3.0
Requires-Dist: click ==8.1.7
Requires-Dist: configobj ==5.0.9
Requires-Dist: configparser ==7.1.0
Requires-Dist: defusedxml ==0.7.1
Requires-Dist: docutils ==0.21.2
Requires-Dist: EbookLib ==0.18
Requires-Dist: etelemetry ==0.3.1
Requires-Dist: filelock ==3.16.1
Requires-Dist: fitz ==0.0.1.dev2
Requires-Dist: httplib2 ==0.22.0
Requires-Dist: idna ==3.10
Requires-Dist: importlib-metadata ==8.5.0
Requires-Dist: importlib-resources ==6.4.5
Requires-Dist: isodate ==0.6.1
Requires-Dist: jaraco.classes ==3.4.0
Requires-Dist: jaraco.context ==6.0.1
Requires-Dist: jaraco.functools ==4.1.0
Requires-Dist: keyring ==25.4.1
Requires-Dist: looseversion ==1.3.0
Requires-Dist: lxml ==5.3.0
Requires-Dist: markdown-it-py ==3.0.0
Requires-Dist: mdurl ==0.1.2
Requires-Dist: more-itertools ==10.5.0
Requires-Dist: networkx ==3.3
Requires-Dist: nh3 ==0.2.18
Requires-Dist: nibabel ==5.3.0
Requires-Dist: nipype ==1.8.6
Requires-Dist: numpy ==2.1.2
Requires-Dist: odfpy ==1.4.1
Requires-Dist: opencv-python ==4.10.0.84
Requires-Dist: packaging ==24.1
Requires-Dist: pandas ==2.2.3
Requires-Dist: pathlib ==1.0.1
Requires-Dist: pdfkit ==1.0.0
Requires-Dist: pillow ==10.4.0
Requires-Dist: pkginfo ==1.10.0
Requires-Dist: prov ==2.0.1
Requires-Dist: pydot ==3.0.2
Requires-Dist: Pygments ==2.18.0
Requires-Dist: PyMuPDF ==1.24.11
Requires-Dist: pyparsing ==3.1.4
Requires-Dist: pytesseract ==0.3.13
Requires-Dist: python-dateutil ==2.9.0.post0
Requires-Dist: python-docx ==1.1.2
Requires-Dist: pytz ==2024.2
Requires-Dist: pyxnat ==1.6.2
Requires-Dist: rdflib ==6.3.2
Requires-Dist: readme-renderer ==44.0
Requires-Dist: reportlab ==4.2.5
Requires-Dist: requests ==2.32.3
Requires-Dist: requests-toolbelt ==1.0.0
Requires-Dist: rfc3986 ==2.0.0
Requires-Dist: rich ==13.9.2
Requires-Dist: scipy ==1.14.1
Requires-Dist: simplejson ==3.19.3
Requires-Dist: six ==1.16.0
Requires-Dist: soupsieve ==2.6
Requires-Dist: traits ==6.3.2
Requires-Dist: twine ==5.1.1
Requires-Dist: typing-extensions ==4.12.2
Requires-Dist: tzdata ==2024.2
Requires-Dist: urllib3 ==2.2.3
Requires-Dist: zipp ==3.20.2
